ibm_watsonx_gov_catalog_mcp_server/__init__.py
ibm_watsonx_gov_catalog_mcp_server/__main__.py
ibm_watsonx_gov_catalog_mcp_server/server.py
ibm_watsonx_gov_catalog_mcp_server/utils/__init__.py
ibm_watsonx_gov_catalog_mcp_server/utils/catalog_utils.py
ibm_watsonx_gov_catalog_mcp_server/utils/mcp_utils.py
ibm_watsonx_gov_catalog_mcp_server-1.0.0.dist-info/METADATA
ibm_watsonx_gov_catalog_mcp_server-1.0.0.dist-info/WHEEL
ibm_watsonx_gov_catalog_mcp_server-1.0.0.dist-info/entry_points.txt
ibm_watsonx_gov_catalog_mcp_server-1.0.0.dist-info/licenses/LICENSE
ibm_watsonx_gov_catalog_mcp_server-1.0.0.dist-info/RECORD
