Metadata-Version: 2.4
Name: ibm-watsonx-gov-catalog-mcp-server
Version: 1.0.0
Summary: An IBM watsonx.governance mcp server that connects AI agents with marketplace of tools available on governance catalog 
Project-URL: Repository, https://github.com/IBM/ibm-watsonx-gov-catalog-mcp-server.git
Project-URL: Bug Tracker, https://github.com/IBM/ibm-watsonx-gov-catalog-mcp-server/issues
Author: IBM watsonx.governance
License: Apache-2.0
License-File: LICENSE
Requires-Python: >=3.11
Requires-Dist: anyio>=4.5
Requires-Dist: click>=8.1.0
Requires-Dist: ibm-watsonx-gov[tools]
Requires-Dist: mcp[cli]>=1.7.1
